cleanup_utils/__init__.py
cleanup_utils/config.py
cleanup_utils/mac_clean_library_cache.py
cleanup_utils/utils.py
cleanup_utils-2.0.0.dist-info/LICENSE
cleanup_utils-2.0.0.dist-info/METADATA
cleanup_utils-2.0.0.dist-info/WHEEL
cleanup_utils-2.0.0.dist-info/entry_points.txt
cleanup_utils-2.0.0.dist-info/RECORD
