Metadata-Version: 2.1
Name: cleanup-utils
Version: 2.0.0
Summary: Utility scripts to clean up your system
Home-page: https://github.com/tddschn/cleanup-utils
License: MIT
Keywords: cleanup,utils
Author: Teddy Xinyuan Chen
Author-email: 45612704+tddschn@users.noreply.github.com
Requires-Python: >=3.10,<4.0
Classifier: License :: OSI Approved :: MIT License
Classifier: Programming Language :: Python :: 3
Classifier: Programming Language :: Python :: 3.10
Classifier: Programming Language :: Python :: 3.11
Classifier: Programming Language :: Python :: 3.12
Classifier: Programming Language :: Python :: 3.13
Classifier: Topic :: Utilities
Requires-Dist: pyyaml (>=6.0.1,<7.0.0)
Project-URL: Bug Tracker, https://github.com/tddschn/cleanup-utils/issues
Project-URL: Repository, https://github.com/tddschn/cleanup-utils
